pyanfis/__init__.py
pyanfis/anfis.py
pyanfis/algorithms/LSTSQ.py
pyanfis/algorithms/RLSE.py
pyanfis/algorithms/__init__.py
pyanfis/algorithms/algorithm.py
pyanfis/antecedents/__init__.py
pyanfis/antecedents/antecedents.py
pyanfis/consequents/__init__.py
pyanfis/consequents/consequents.py
pyanfis/consequents/types/lee.py
pyanfis/consequents/types/takagi_sugeno.py
pyanfis/consequents/types/tsukamoto.py
pyanfis/functions/__init__.py
pyanfis/functions/bell.py
pyanfis/functions/gauss.py
pyanfis/functions/heaviside.py
pyanfis/functions/linear_s.py
pyanfis/functions/linear_z.py
pyanfis/functions/sigmoid.py
pyanfis/functions/triangular.py
pyanfis/functions/universe.py
pyanfis/functions/utils.py
pyanfis/pyplot/__init__.py
pyanfis/pyplot/functions_plotting.py
pyanfis/pyplot/structure_plotting.py
pyanfis/rules/__init__.py
pyanfis/rules/intersection_algorithms.py
pyanfis/rules/relation_algorithms.py
pyanfis/rules/rules.py
pyanfis-0.1.11.dist-info/LICENSE
pyanfis-0.1.11.dist-info/METADATA
pyanfis-0.1.11.dist-info/WHEEL
pyanfis-0.1.11.dist-info/top_level.txt
pyanfis-0.1.11.dist-info/RECORD
