Metadata-Version: 2.1
Name: pyanfis
Version: 0.1.11
Summary: A pytorch-based package to use ANFIS for AI
Author-email: Vicente Feced Mas <vicente.feced.mas@gmail.com>
Project-URL: Homepage, https://github.com/VicenteFecedMas/pyanfis
Classifier: Programming Language :: Python :: 3
Classifier: License :: OSI Approved :: MIT License
Classifier: Operating System :: OS Independent
Requires-Python: >=3.11
License-File: LICENSE
